<?xml version="1.0" encoding="utf-8" ?>
<dwsync>
<file name="array_helper.html" server="127.0.0.1/mongeral/" local="131290624333948341" remote="131290622400000000" Dst="2" />
<file name="captcha_helper.html" server="127.0.0.1/mongeral/" local="131290624334048446" remote="131290622400000000" Dst="2" />
<file name="cookie_helper.html" server="127.0.0.1/mongeral/" local="131290624334103455" remote="131290622400000000" Dst="2" />
<file name="date_helper.html" server="127.0.0.1/mongeral/" local="131290624334158494" remote="131290622400000000" Dst="2" />
<file name="directory_helper.html" server="127.0.0.1/mongeral/" local="131290624334223540" remote="131290622400000000" Dst="2" />
<file name="download_helper.html" server="127.0.0.1/mongeral/" local="131290624334283579" remote="131290622400000000" Dst="2" />
<file name="email_helper.html" server="127.0.0.1/mongeral/" local="131290624334338622" remote="131290622400000000" Dst="2" />
<file name="file_helper.html" server="127.0.0.1/mongeral/" local="131290624334398665" remote="131290622400000000" Dst="2" />
<file name="form_helper.html" server="127.0.0.1/mongeral/" local="131290624334453700" remote="131290622400000000" Dst="2" />
<file name="html_helper.html" server="127.0.0.1/mongeral/" local="131290624334518755" remote="131290622400000000" Dst="2" />
<file name="index.html" server="127.0.0.1/mongeral/" local="131290624334583809" remote="131290622400000000" Dst="2" />
<file name="inflector_helper.html" server="127.0.0.1/mongeral/" local="131290624334623838" remote="131290622400000000" Dst="2" />
<file name="language_helper.html" server="127.0.0.1/mongeral/" local="131290624334678868" remote="131290622400000000" Dst="2" />
<file name="number_helper.html" server="127.0.0.1/mongeral/" local="131290624334733899" remote="131290622400000000" Dst="2" />
<file name="path_helper.html" server="127.0.0.1/mongeral/" local="131290624334793954" remote="131290622400000000" Dst="2" />
<file name="security_helper.html" server="127.0.0.1/mongeral/" local="131290624336039827" remote="131290622400000000" Dst="2" />
<file name="smiley_helper.html" server="127.0.0.1/mongeral/" local="131290624336134912" remote="131290622400000000" Dst="2" />
<file name="string_helper.html" server="127.0.0.1/mongeral/" local="131290624336174927" remote="131290622400000000" Dst="2" />
<file name="text_helper.html" server="127.0.0.1/mongeral/" local="131290624336234983" remote="131290622400000000" Dst="2" />
<file name="typography_helper.html" server="127.0.0.1/mongeral/" local="131290624336295017" remote="131290622400000000" Dst="2" />
<file name="url_helper.html" server="127.0.0.1/mongeral/" local="131290624336365062" remote="131290622400000000" Dst="2" />
<file name="xml_helper.html" server="127.0.0.1/mongeral/" local="131290624336410094" remote="131290622400000000" Dst="2" />
</dwsync>